django_new_preferences-0.2.dist-info/METADATA
django_new_preferences-0.2.dist-info/RECORD
django_new_preferences-0.2.dist-info/WHEEL
django_new_preferences-0.2.dist-info/top_level.txt
preferences/__init__.py
preferences/admin.py
preferences/context_processors.py
preferences/managers.py
preferences/models.py
preferences/migrations/0001_initial.py
preferences/migrations/__init__.py
preferences/tests/__init__.py
preferences/tests/admin.py
preferences/tests/manage.py
preferences/tests/models.py
preferences/tests/test_all.py
preferences/tests/urls.py
preferences/tests/migrations/0001_initial.py
preferences/tests/migrations/__init__.py
preferences/tests/requirements/110.txt
preferences/tests/requirements/111.txt
preferences/tests/requirements/20.txt
preferences/tests/settings/110.py
preferences/tests/settings/111.py
preferences/tests/settings/20.py
preferences/tests/settings/__init__.py
