Metadata-Version: 2.1
Name: django-new-preferences
Version: 0.2
Summary: Django app allowing users to set app specific preferences through the admin interface.
Home-page: http://github.com/praekelt/django-new-preferences
Author: Praekelt Consulting
Author-email: dev@praekelt.com
License: BSD
Platform: UNKNOWN
Classifier: Programming Language :: Python
Classifier: License :: OSI Approved :: BSD License
Classifier: Development Status :: 5 - Production/Stable
Classifier: Operating System :: OS Independent
Classifier: Framework :: Django
Classifier: Intended Audience :: Developers
Classifier: Topic :: Internet :: WWW/HTTP :: Dynamic Content
Requires-Dist: django
